[
	{
		"anonymous": false,
		"inputs": [
			{
				"indexed": true,
				"internalType": "address",
				"name": "_poolOwner",
				"type": "address"
			},
			{
				"indexed": true,
				"internalType": "address",
				"name": "_stakeTokenAddr",
				"type": "address"
			},
			{
				"indexed": true,
				"internalType": "address",
				"name": "_rewardTokenAddr",
				"type": "address"
			},
			{
				"indexed": false,
				"internalType": "uint256",
				"name": "_rewardPerMin",
				"type": "uint256"
			}
		],
		"name": "PoolAdded",
		"type": "event"
	},
	{
		"inputs": [
			{
				"internalType": "address",
				"name": "nft",
				"type": "address"
			},
			{
				"internalType": "string",
				"name": "_poolName",
				"type": "string"
			},
			{
				"internalType": "address",
				"name": "_stakeTokenAddr",
				"type": "address"
			},
			{
				"internalType": "address",
				"name": "_rewardTokenAddr",
				"type": "address"
			},
			{
				"internalType": "uint256",
				"name": "_rewardPerMin",
				"type": "uint256"
			},
			{
				"internalType": "address",
				"name": "_slotContractAddress",
				"type": "address"
			}
		],
		"name": "addPool",
		"outputs": [],
		"stateMutability": "nonpayable",
		"type": "function"
	},
	{
		"inputs": [],
		"name": "getAllPools",
		"outputs": [
			{
				"internalType": "address[]",
				"name": "",
				"type": "address[]"
			}
		],
		"stateMutability": "view",
		"type": "function"
	},
	{
		"inputs": [
			{
				"internalType": "address",
				"name": "_owner",
				"type": "address"
			}
		],
		"name": "getOwnerPoolInfos",
		"outputs": [
			{
				"components": [
					{
						"internalType": "address",
						"name": "owner",
						"type": "address"
					},
					{
						"internalType": "address",
						"name": "nft",
						"type": "address"
					},
					{
						"internalType": "string",
						"name": "poolName",
						"type": "string"
					},
					{
						"internalType": "uint256",
						"name": "slotsNum",
						"type": "uint256"
					},
					{
						"internalType": "uint256",
						"name": "membersNum",
						"type": "uint256"
					}
				],
				"internalType": "struct Pool.PoolInfo[]",
				"name": "",
				"type": "tuple[]"
			}
		],
		"stateMutability": "view",
		"type": "function"
	},
	{
		"inputs": [
			{
				"internalType": "address",
				"name": "_owner",
				"type": "address"
			}
		],
		"name": "getOwnerPools",
		"outputs": [
			{
				"internalType": "address[]",
				"name": "",
				"type": "address[]"
			}
		],
		"stateMutability": "view",
		"type": "function"
	},
	{
		"inputs": [
			{
				"internalType": "uint256",
				"name": "",
				"type": "uint256"
			}
		],
		"name": "pools",
		"outputs": [
			{
				"internalType": "address",
				"name": "",
				"type": "address"
			}
		],
		"stateMutability": "view",
		"type": "function"
	}
]
